facata/__init__.py
facata/_version.py
facata/core.py
facata/exceptions.py
facata/mariadb_mariadb.py
facata/mysql_mysqlconnector.py
facata/postgresql_pg8000.py
facata/postgresql_psycopg2.py
facata/sqlite_sqlite3.py
facata/utils.py
facata-0.1.0.dist-info/LICENSE
facata-0.1.0.dist-info/METADATA
facata-0.1.0.dist-info/WHEEL
facata-0.1.0.dist-info/top_level.txt
facata-0.1.0.dist-info/RECORD
